quantimpy/__init__.py
quantimpy/brisque.cpython-37m-darwin.so
quantimpy/minkowski.cpython-37m-darwin.so
quantimpy/morphology.py
quantimpy/segmentation.cpython-37m-darwin.so
quantimpy-0.4.6.dist-info/LICENSE
quantimpy-0.4.6.dist-info/METADATA
quantimpy-0.4.6.dist-info/WHEEL
quantimpy-0.4.6.dist-info/top_level.txt
quantimpy-0.4.6.dist-info/RECORD
